langgraph_sdk/__init__.py
langgraph_sdk/client.py
langgraph_sdk/py.typed
langgraph_sdk/schema.py
langgraph_sdk/sse.py
langgraph_sdk/auth/__init__.py
langgraph_sdk/auth/exceptions.py
langgraph_sdk/auth/types.py
langgraph_sdk-0.2.1.dist-info/METADATA
langgraph_sdk-0.2.1.dist-info/WHEEL
langgraph_sdk-0.2.1.dist-info/licenses/LICENSE
langgraph_sdk-0.2.1.dist-info/RECORD
