Metadata-Version: 2.4
Name: langgraph-sdk
Version: 0.2.1
Summary: SDK for interacting with LangGraph API
Project-URL: Repository, https://www.github.com/langchain-ai/langgraph
License-Expression: MIT
License-File: LICENSE
Requires-Python: >=3.9
Requires-Dist: httpx>=0.25.2
Requires-Dist: orjson>=3.10.1
